{
  "_fv": 66,
  "_type": "gui",
  "definition": {
    "type": 0,
    "width": 251,
    "height": 154,
    "inventoryOffsetX": 0,
    "inventoryOffsetY": 0,
    "renderBgLayer": true,
    "doesPauseGame": false,
    "components": [
      {
        "type": "button",
        "data": {
          "name": "button_empty",
          "text": "^",
          "isUndecorated": false,
          "onClick": {
            "name": "OnUpgradeButtonPressed"
          },
          "width": 30,
          "height": 20,
          "x": 100,
          "y": 87
        }
      },
      {
        "type": "label",
        "data": {
          "name": "label_upgrade_speed_0002",
          "text": {
            "fixedValue": "Upgrade Speed (+0,002) -"
          },
          "color": {
            "value": -12829636,
            "falpha": 0.0
          },
          "x": 138,
          "y": 85
        }
      },
      {
        "type": "label",
        "data": {
          "name": "label_lvl_varintegerhorselvl_v",
          "text": {
            "fixedValue": "LvL. <VAR:integer:horseLvl> ( <VAR:horseMoveSpeed> MS)"
          },
          "color": {
            "value": -12829636,
            "falpha": 0.0
          },
          "x": 138,
          "y": 99
        }
      },
      {
        "type": "label",
        "data": {
          "name": "label_varintegerhorsemscorneededk",
          "text": {
            "fixedValue": "<VAR:integer:horseMSCorNeeded>k Cor"
          },
          "color": {
            "value": -10496,
            "falpha": 0.0
          },
          "x": 277,
          "y": 86
        }
      },
      {
        "type": "button",
        "data": {
          "name": "button_change_color",
          "text": "Change Color",
          "isUndecorated": false,
          "onClick": {
            "name": "OnHorseChangeColorPressed"
          },
          "width": 87,
          "height": 20,
          "x": 110,
          "y": 146
        }
      },
      {
        "type": "button",
        "data": {
          "name": "button_change_pattern",
          "text": "change pattern",
          "isUndecorated": false,
          "onClick": {
            "name": "OnHorsePatternChangePressed"
          },
          "width": 98,
          "height": 20,
          "x": 218,
          "y": 146
        }
      },
      {
        "type": "label",
        "data": {
          "name": "label_your_cor_varintegercor",
          "text": {
            "fixedValue": "(Your Cor: <VAR:integer:cor>)"
          },
          "color": {
            "value": -12829636,
            "falpha": 0.0
          },
          "x": 145,
          "y": 175
        }
      }
    ],
    "gridSettings": {
      "sx": 18,
      "sy": 18,
      "ox": 11,
      "oy": 15,
      "snapOnGrid": false
    }
  }
}